<?xml version="1.0"?>
<level>
	<map>
		<line><cell value="-1" /><cell value="-1" /><cell value="-1" /><cell value="-1" /><cell value="-1" /><cell value="-1" /><cell value="-1" /><cell value="-1" /></line>
		<line><cell value="-1" /><cell value="1" /><cell value="1" /><cell value="1" /><cell value="1" /><cell value="1" /><cell value="1" /><cell value="-1" /></line>
		<line><cell value="-1" /><cell value="3" /><cell value="0" /><cell value="0" /><cell value="0" /><cell value="2" /><cell value="1" /><cell value="-1" /></line>
		<line><cell value="-1" /><cell value="1" /><cell value="1" /><cell value="1" /><cell value="1" /><cell value="0" /><cell value="1" /><cell value="-1" /></line>
		<line><cell value="-1" /><cell value="-1" /><cell value="-1" /><cell value="-1" /><cell value="-1" /><cell value="-1" /><cell value="-1" /><cell value="-1" /></line>
	</map>

	<dialogs>
		<dialog text="[fr]Il faut continuer à avancer.[/fr][en]We need to keep moving forward.[/en]" enableInteraction="0" briefingType="0" />
		<dialog text="[fr]Au fait, notre drone d'observation suis automatiquement le déplacement de Plok mais tu peux le contrôler avec les boutons situés en bas à droite du jeu. N'hésite pas à expérimenter ces commandes.[/fr][en]One comment, our observation drone automatically follows Plok's movements, but you can control it using the buttons at the bottom right of the game. Feel free to experiment with these controls.[/en]" img="../../Tutoriel/Images/cameraControl.png" imgDesc="[fr]Illustration montrant le panneau de contrôle de la caméra.[/fr][en]Illustration showing the camera's control panel.[/en]" imgHeight="110" enableInteraction="0" briefingType="0" />
	</dialogs>
	<score twoStars="5000" threeStars="6000"/>

	<blockLimits>
		<blockLimit blockType="Forward" limit="4" />
		<blockLimit blockType="TurnLeft" limit="0" />
		<blockLimit blockType="TurnRight" limit="0" />
		<blockLimit blockType="TurnBack" limit="0" />
		<blockLimit blockType="Activate" limit="0" />
		<blockLimit blockType="Wait" limit="0" />
		<blockLimit blockType="IfThen" limit="0" />
		<blockLimit blockType="IfElse" limit="0" />
		<blockLimit blockType="ForLoop" limit="0" />
		<blockLimit blockType="While" limit="0" />
		<blockLimit blockType="Forever" limit="0" />
		<blockLimit blockType="AndOperator" limit="0" />
		<blockLimit blockType="OrOperator" limit="0" />
		<blockLimit blockType="NotOperator" limit="0" />
		<blockLimit blockType="WallFront" limit="0" />
		<blockLimit blockType="WallLeft" limit="0" />
		<blockLimit blockType="WallRight" limit="0" />
		<blockLimit blockType="PathFront" limit="0" />
		<blockLimit blockType="PathLeft" limit="0" />
		<blockLimit blockType="PathRight" limit="0" />
		<blockLimit blockType="Enemy" limit="0" />
		<blockLimit blockType="RedArea" limit="0" />
		<blockLimit blockType="Player" limit="0" />
		<blockLimit blockType="Furniture" limit="0" />
		<blockLimit blockType="FieldGate" limit="0" />
		<blockLimit blockType="Terminal" limit="0" />
		<blockLimit blockType="Exit" limit="0" />
	</blockLimits>

	<robot inputLine="Plok" posX="5" posY="2" direction="3" skin="0" />

	<script outputLine="Plok" editMode="0" type="3">
	</script>

	<script outputLine="Plok_Sol" editMode="2" type="4">
		<action type="Forward"/>
		<action type="Forward"/>
		<action type="Forward"/>
		<action type="Forward"/>
	</script>

</level>