<?xml version="1.0"?>
<level>
  <info>
    <func name="F5"/>
    <func name="F8"/>
    <func name="F17"/>
  </info>
  <map>
    <line>
      <row value="-1" />
      <row value="1" />
      <row value="1" />
      <row value="1" />
      <row value="1" />
    </line>
    <line>
      <row value="-1" />
      <row value="1" />
      <row value="0" />
      <row value="3" />
      <row value="1" />
    </line>
    <line>
      <row value="-1" />
      <row value="1" />
      <row value="0" />
      <row value="1" />
      <row value="1" />
    </line>
    <line>
      <row value="1" />
      <row value="1" />
      <row value="0" />
      <row value="1" />
      <row value="1" />
    </line>
    <line>
      <row value="1" />
      <row value="0" />
      <row value="2" />
      <row value="0" />
      <row value="1" />
    </line>
    <line>
      <row value="1" />
      <row value="1" />
      <row value="1" />
      <row value="1" />
      <row value="1" />
    </line>
  </map>
  <actionBlockLimit>
    <limit actionType="Forward" limit="-1" />
    <limit actionType="TurnLeft" limit="-1" />
    <limit actionType="TurnRight" limit="-1" />
    <limit actionType="TurnBack" limit="-1" />
    <limit actionType="Activate" limit="-1" />
    <limit actionType="Wait" limit="-1" />
    <limit actionType="If" limit="0" />
    <limit actionType="IfElse" limit="0" />
    <limit actionType="For" limit="0" />
    <limit actionType="Forever" limit="0" />
    <limit actionType="While" limit="0" />
    <limit actionType="AndOperator" limit="0" />
    <limit actionType="OrOperator" limit="0" />
    <limit actionType="NotOperator" limit="0" />
    <limit actionType="Wall" limit="0" />
    <limit actionType="Enemie" limit="0" />
    <limit actionType="RedArea" limit="0" />
    <limit actionType="FieldGate" limit="0" />
    <limit actionType="Terminal" limit="0" />
    <limit actionType="Exit" limit="0" />
  </actionBlockLimit>
  <player associatedScriptName="Agent 1" posX="4" posZ="2" direction="3">
  <script name="Agent 1" editMode="0">
      <action type="TurnRight"/>
      <action type="Forward"/>
      <action type="Activate"/>
      <action type="TurnBack"/>
      <action type="TurnRight"/>
      <action type="Forward"/>
      <action type="Forward"/>
      <action type="Forward"/>
      <action type="TurnRight"/>
      <action type="Forward"/>
  </script>
  <score twoStars="7999" threeStars="10500"/>
  <console posX="4" posZ="1" direction="1">
    <slot slot="0" />
  </console>
  <door posX="2" posZ="2" slot="0" direction="3" />
</level>